magellantools/ALTEDR.py
magellantools/ARCDR.py
magellantools/script/arcdr2table.py
magellantools-0.0.2.dist-info/LICENSE
magellantools-0.0.2.dist-info/METADATA
magellantools-0.0.2.dist-info/WHEEL
magellantools-0.0.2.dist-info/entry_points.txt
magellantools-0.0.2.dist-info/top_level.txt
magellantools-0.0.2.dist-info/RECORD
