Metadata-Version: 2.1
Name: magellantools
Version: 0.0.2
Summary: Tools to parse and manipulate data from the Magellan mission stored on NASA's PDS
Author-email: Indujaa Ganesh <indujaa.ganesh@gmail.com>, Michael Christoffersen <mchristo28@gmail.com>
Project-URL: repository, https://github.com/iganache/magellantools
Project-URL: documentation, https://magellantools.readthedocs.io/en/latest/
Requires-Python: >=3.6
License-File: LICENSE
Requires-Dist: numpy
Requires-Dist: pandas
Requires-Dist: geopandas
Requires-Dist: tqdm
